mycalc/calculator.py
byoungpil-0.0.1.dist-info/METADATA
byoungpil-0.0.1.dist-info/WHEEL
byoungpil-0.0.1.dist-info/top_level.txt
byoungpil-0.0.1.dist-info/RECORD
