Metadata-Version: 2.1
Name: byoungpil
Version: 0.0.1
Summary: nice calculator
Home-page: https://github.com/parkbyoungpil/oss-creative
Download-URL: https://github.com/parkbyoungpil/oss-creative
Author: parkbyoungpil
License: UNKNOWN
Platform: UNKNOWN
Classifier: Programming Language :: Python :: 3
